rest_lx/__init__.py
rest_lx/rest.py
websocket_lx/__init__.py
websocket_lx/client.py
websocket_lx/websocket_manager.py
ftxusderivatives_python-0.1.2.dist-info/LICENSE
ftxusderivatives_python-0.1.2.dist-info/WHEEL
ftxusderivatives_python-0.1.2.dist-info/METADATA
ftxusderivatives_python-0.1.2.dist-info/RECORD
