Metadata-Version: 2.1
Name: ftxusderivatives-python
Version: 0.1.2
Summary: An unofficial Python wrapper for the REST and WebSocket APIs of FTX US Derivatives, formerly known as LedgerX.
Home-page: https://github.com/nenyehub/ftxusderivatives-python
License: MIT
Keywords: FTX,trading,crypto
Author: Nenye Ndili
Author-email: nenye@ndili.net
Requires-Python: >=3.7,<4.0
Classifier: Intended Audience :: Developers
Classifier: License :: OSI Approved :: MIT License
Classifier: Natural Language :: English
Classifier: Programming Language :: Python :: 3
Classifier: Programming Language :: Python :: 3.10
Classifier: Programming Language :: Python :: 3.7
Classifier: Programming Language :: Python :: 3.8
Classifier: Programming Language :: Python :: 3.9
Requires-Dist: requests (>=2.27.1,<3.0.0)
Requires-Dist: websocket-client (>=1.3.1,<2.0.0)
Project-URL: Repository, https://github.com/nenyehub/ftxusderivatives-python
